audio_diffusion_pytorch/__init__.py
audio_diffusion_pytorch/components.py
audio_diffusion_pytorch/diffusion.py
audio_diffusion_pytorch/models.py
audio_diffusion_pytorch/utils.py
audio_diffusion_pytorch-0.1.3.dist-info/LICENSE
audio_diffusion_pytorch-0.1.3.dist-info/METADATA
audio_diffusion_pytorch-0.1.3.dist-info/WHEEL
audio_diffusion_pytorch-0.1.3.dist-info/top_level.txt
audio_diffusion_pytorch-0.1.3.dist-info/RECORD
