Metadata-Version: 2.1
Name: audio-diffusion-pytorch
Version: 0.1.3
Summary: Audio Diffusion - PyTorch
Home-page: https://github.com/archinetai/audio-diffusion-pytorch
Author: Flavio Schneider
Author-email: archinetai@protonmail.com
License: MIT
Keywords: artificial intelligence,deep learning,audio generation
Classifier: Development Status :: 4 - Beta
Classifier: Intended Audience :: Developers
Classifier: Topic :: Scientific/Engineering :: Artificial Intelligence
Classifier: License :: OSI Approved :: MIT License
Classifier: Programming Language :: Python :: 3.6
License-File: LICENSE
Requires-Dist: tqdm
Requires-Dist: torch (>=1.6)
Requires-Dist: torchaudio
Requires-Dist: data-science-types (>=0.2)
Requires-Dist: einops (>=0.6)
Requires-Dist: a-unet
